cocalc/__init__.py
cocalc/api.py
cocalc/constants.py
cocalc/exceptions.py
cocalc/responses.py
cocalc_python-0.0.4.dist-info/LICENSE
cocalc_python-0.0.4.dist-info/METADATA
cocalc_python-0.0.4.dist-info/WHEEL
cocalc_python-0.0.4.dist-info/top_level.txt
cocalc_python-0.0.4.dist-info/RECORD
